eia/__init__.py
eia/api.py
eia_python-1.22.dist-info/METADATA
eia_python-1.22.dist-info/RECORD
eia_python-1.22.dist-info/WHEEL
eia_python-1.22.dist-info/top_level.txt
