Metadata-Version: 1.0
Name: eia-python
Version: 1.22
Summary: Python Wrapper for the Energy Information Administration (eia) API
Home-page: https://github.com/mra1385/eia-python
Author: Mike Azar
Author-email: mikeazar@gmail.com
License: BSD
Platform: UNKNOWN
